Printer/__init__.py
Print_clor-0.1.dist-info/METADATA
Print_clor-0.1.dist-info/WHEEL
Print_clor-0.1.dist-info/top_level.txt
Print_clor-0.1.dist-info/RECORD
